{
  "point_id": "v_0p70_t_0p70_lm_1p00",
  "params": {
    "v": 0.7,
    "t": 0.7,
    "lm": 1.0
  },
  "category": "near_transition",
  "invariants": {
    "gap": 0.0,
    "z2": 0,
    "chern": 5.30092447e-16,
    "wilson": -0.25433305
  },
  "window": {
    "old_center": -0.0009701180171764372,
    "zero_window": [
      -0.25,
      0.25
    ],
    "ribbon_window": [
      1.499719587306378,
      2.246190999292538
    ],
    "ribbon_center": 1.872955293299458
  },
  "weights": {
    "old": {
      "W_left": 0.1201058299751836,
      "W_right": 0.12010582997518356,
      "W_top": 0.12010582997518353,
      "W_bottom": 0.12010582997518365,
      "W_edge_total": 0.38559572673061304,
      "W_corner": 0.22729345303065634,
      "W_bulk": 0.5902799252614048
    },
    "best_edge": {
      "W_left": 0.1605361608559441,
      "W_right": 0.1605361608559439,
      "W_top": 0.1605361608559441,
      "W_bottom": 0.16053616085594388,
      "W_edge_total": 0.5907128504646195,
      "W_corner": 0.12965643715962155,
      "W_bulk": 0.3956222155155087
    },
    "best_corner": {
      "W_left": 0.1477599806253638,
      "W_right": 0.1477599806253634,
      "W_top": 0.14775998062536366,
      "W_bottom": 0.14775998062536344,
      "W_edge_total": 0.4620461148159064,
      "W_corner": 0.24291172543990497,
      "W_bulk": 0.5256142318705757
    },
    "rotated_edge": {
      "W_left": 0.1605361608559441,
      "W_right": 0.1605361608559439,
      "W_top": 0.1605361608559441,
      "W_bottom": 0.16053616085594388,
      "W_edge_total": 0.5907128504646195,
      "W_corner": 0.12965643715962155,
      "W_bulk": 0.3956222155155087
    },
    "rotated_corner": {
      "W_left": 0.1477599806253638,
      "W_right": 0.1477599806253634,
      "W_top": 0.14775998062536366,
      "W_bottom": 0.14775998062536344,
      "W_edge_total": 0.4620461148159064,
      "W_corner": 0.24291172543990497,
      "W_bulk": 0.5256142318705757
    }
  },
  "side_states": {
    "left": {
      "energy": 0.035781094658206475,
      "side_weight": 0.1605361608559441,
      "all_side_weights": {
        "left": 0.1605361608559441,
        "right": 0.1605361608559439,
        "top": 0.1605361608559441,
        "bottom": 0.16053616085594388
      }
    },
    "right": {
      "energy": 0.03578109465820633,
      "side_weight": 0.16053616085594427,
      "all_side_weights": {
        "left": 0.1605361608559437,
        "right": 0.16053616085594427,
        "top": 0.1605361608559444,
        "bottom": 0.16053616085594352
      }
    },
    "top": {
      "energy": 0.03578109465820633,
      "side_weight": 0.1605361608559444,
      "all_side_weights": {
        "left": 0.1605361608559437,
        "right": 0.16053616085594427,
        "top": 0.1605361608559444,
        "bottom": 0.16053616085594352
      }
    },
    "bottom": {
      "energy": 0.035781094658206475,
      "side_weight": 0.16053616085594388,
      "all_side_weights": {
        "left": 0.1605361608559441,
        "right": 0.1605361608559439,
        "top": 0.1605361608559441,
        "bottom": 0.16053616085594388
      }
    }
  },
  "methods": {
    "old_mode_energy": -0.0009701180171764372,
    "best_edge_energy": 0.035781094658206475,
    "best_corner_energy": -0.10124868217256454,
    "rotated_edge_energy": 0.035781094658206475,
    "rotated_corner_energy": -0.10124868217256454
  },
  "degenerate_groups": [
    {
      "point_id": "v_0p70_t_0p70_lm_1p00",
      "group_id": 0,
      "dim": 4,
      "E_min": -0.5314752846165542,
      "E_max": -0.5303408690773791,
      "delta_E": 0.0011344155391751487,
      "best_edge_projection_after": 0.3868904446959929,
      "best_corner_projection_after": 0.054785085216387794
    },
    {
      "point_id": "v_0p70_t_0p70_lm_1p00",
      "group_id": 1,
      "dim": 6,
      "E_min": -0.5200019814043169,
      "E_max": -0.5162077718453453,
      "delta_E": 0.003794209558971584,
      "best_edge_projection_after": 0.47895896439939695,
      "best_corner_projection_after": 0.15409850642625755
    },
    {
      "point_id": "v_0p70_t_0p70_lm_1p00",
      "group_id": 2,
      "dim": 10,
      "E_min": -0.4975194229052931,
      "E_max": -0.4882398601501749,
      "delta_E": 0.00927956275511821,
      "best_edge_projection_after": 0.486439245508045,
      "best_corner_projection_after": 0.1636082492080853
    },
    {
      "point_id": "v_0p70_t_0p70_lm_1p00",
      "group_id": 3,
      "dim": 2,
      "E_min": -0.4778054280017766,
      "E_max": -0.4778054280017729,
      "delta_E": 3.7192471324942744e-15,
      "best_edge_projection_after": 0.29752759785655036,
      "best_corner_projection_after": 0.15089972032747404
    },
    {
      "point_id": "v_0p70_t_0p70_lm_1p00",
      "group_id": 4,
      "dim": 2,
      "E_min": -0.4725020477553281,
      "E_max": -0.47250204775532356,
      "delta_E": 4.551914400963142e-15,
      "best_edge_projection_after": 0.4182342928541831,
      "best_corner_projection_after": 0.1533283905696441
    },
    {
      "point_id": "v_0p70_t_0p70_lm_1p00",
      "group_id": 5,
      "dim": 6,
      "E_min": -0.46326164661003894,
      "E_max": -0.4619015046990754,
      "delta_E": 0.0013601419109635082,
      "best_edge_projection_after": 0.4458745066449663,
      "best_corner_projection_after": 0.11029615826249427
    },
    {
      "point_id": "v_0p70_t_0p70_lm_1p00",
      "group_id": 6,
      "dim": 6,
      "E_min": -0.4540537136721525,
      "E_max": -0.45242349485621997,
      "delta_E": 0.0016302188159325604,
      "best_edge_projection_after": 0.4408839707196427,
      "best_corner_projection_after": 0.15909125873473082
    },
    {
      "point_id": "v_0p70_t_0p70_lm_1p00",
      "group_id": 7,
      "dim": 4,
      "E_min": -0.4475751399102965,
      "E_max": -0.4455775408483546,
      "delta_E": 0.0019975990619419126,
      "best_edge_projection_after": 0.5071770336648548,
      "best_corner_projection_after": 0.12766026288000568
    },
    {
      "point_id": "v_0p70_t_0p70_lm_1p00",
      "group_id": 8,
      "dim": 2,
      "E_min": -0.4310860014289551,
      "E_max": -0.4310860014289532,
      "delta_E": 1.887379141862766e-15,
      "best_edge_projection_after": 0.48174896920172056,
      "best_corner_projection_after": 0.08186369725202748
    },
    {
      "point_id": "v_0p70_t_0p70_lm_1p00",
      "group_id": 9,
      "dim": 6,
      "E_min": -0.42313394128471166,
      "E_max": -0.4154161645905562,
      "delta_E": 0.007717776694155465,
      "best_edge_projection_after": 0.47048183279307754,
      "best_corner_projection_after": 0.15706539218855484
    },
    {
      "point_id": "v_0p70_t_0p70_lm_1p00",
      "group_id": 10,
      "dim": 2,
      "E_min": -0.4004358369473885,
      "E_max": -0.40043583694738427,
      "delta_E": 4.218847493575595e-15,
      "best_edge_projection_after": 0.34954458118049914,
      "best_corner_projection_after": 0.15017049689270504
    },
    {
      "point_id": "v_0p70_t_0p70_lm_1p00",
      "group_id": 11,
      "dim": 10,
      "E_min": -0.3963929574921071,
      "E_max": -0.3843951103519066,
      "delta_E": 0.011997847140200524,
      "best_edge_projection_after": 0.5259720401777801,
      "best_corner_projection_after": 0.16640844272643543
    },
    {
      "point_id": "v_0p70_t_0p70_lm_1p00",
      "group_id": 12,
      "dim": 2,
      "E_min": -0.38002276820673925,
      "E_max": -0.38002276820673325,
      "delta_E": 5.995204332975845e-15,
      "best_edge_projection_after": 0.4012099602904659,
      "best_corner_projection_after": 0.155289598730101
    },
    {
      "point_id": "v_0p70_t_0p70_lm_1p00",
      "group_id": 13,
      "dim": 4,
      "E_min": -0.375755174266412,
      "E_max": -0.3757537827955532,
      "delta_E": 1.391470858758126e-06,
      "best_edge_projection_after": 0.24034435109837782,
      "best_corner_projection_after": 0.028252474047925774
    },
    {
      "point_id": "v_0p70_t_0p70_lm_1p00",
      "group_id": 14,
      "dim": 2,
      "E_min": -0.3597653799181257,
      "E_max": -0.35976537991812413,
      "delta_E": 1.5543122344752192e-15,
      "best_edge_projection_after": 0.4326348810202055,
      "best_corner_projection_after": 0.09944896815444365
    },
    {
      "point_id": "v_0p70_t_0p70_lm_1p00",
      "group_id": 15,
      "dim": 2,
      "E_min": -0.3524569053028692,
      "E_max": -0.3524569053028679,
      "delta_E": 1.3322676295501878e-15,
      "best_edge_projection_after": 0.4505960233068626,
      "best_corner_projection_after": 0.14862238983017823
    },
    {
      "point_id": "v_0p70_t_0p70_lm_1p00",
      "group_id": 16,
      "dim": 2,
      "E_min": -0.3488412003699947,
      "E_max": -0.34884120036998834,
      "delta_E": 6.38378239159465e-15,
      "best_edge_projection_after": 0.45840538970408085,
      "best_corner_projection_after": 0.1250224214446187
    },
    {
      "point_id": "v_0p70_t_0p70_lm_1p00",
      "group_id": 17,
      "dim": 2,
      "E_min": -0.3412094375665022,
      "E_max": -0.3412094375665016,
      "delta_E": 5.551115123125783e-16,
      "best_edge_projection_after": 0.36992766334775506,
      "best_corner_projection_after": 0.05787146998146971
    },
    {
      "point_id": "v_0p70_t_0p70_lm_1p00",
      "group_id": 18,
      "dim": 6,
      "E_min": -0.3281670484372153,
      "E_max": -0.32232725445152927,
      "delta_E": 0.005839793985686015,
      "best_edge_projection_after": 0.4707609317613481,
      "best_corner_projection_after": 0.1299517438010758
    },
    {
      "point_id": "v_0p70_t_0p70_lm_1p00",
      "group_id": 19,
      "dim": 2,
      "E_min": -0.3146221546295536,
      "E_max": -0.3146221546295528,
      "delta_E": 8.326672684688674e-16,
      "best_edge_projection_after": 0.33220693882100766,
      "best_corner_projection_after": 0.09052411005351368
    },
    {
      "point_id": "v_0p70_t_0p70_lm_1p00",
      "group_id": 20,
      "dim": 2,
      "E_min": -0.3071140137771517,
      "E_max": -0.30711401377714376,
      "delta_E": 7.93809462606987e-15,
      "best_edge_projection_after": 0.29914937168037803,
      "best_corner_projection_after": 0.1009493189310304
    },
    {
      "point_id": "v_0p70_t_0p70_lm_1p00",
      "group_id": 21,
      "dim": 2,
      "E_min": -0.3001463883320616,
      "E_max": -0.3001463883320587,
      "delta_E": 2.886579864025407e-15,
      "best_edge_projection_after": 0.4649803515029639,
      "best_corner_projection_after": 0.13420246301504812
    },
    {
      "point_id": "v_0p70_t_0p70_lm_1p00",
      "group_id": 22,
      "dim": 4,
      "E_min": -0.2970024501162473,
      "E_max": -0.2968626756479828,
      "delta_E": 0.00013977446826451967,
      "best_edge_projection_after": 0.2489737250421992,
      "best_corner_projection_after": 0.024360236096524573
    },
    {
      "point_id": "v_0p70_t_0p70_lm_1p00",
      "group_id": 23,
      "dim": 2,
      "E_min": -0.2869126107128292,
      "E_max": -0.2869126107128281,
      "delta_E": 1.1102230246251565e-15,
      "best_edge_projection_after": 0.4300261433772283,
      "best_corner_projection_after": 0.039533751943390864
    },
    {
      "point_id": "v_0p70_t_0p70_lm_1p00",
      "group_id": 24,
      "dim": 4,
      "E_min": -0.28321530040366144,
      "E_max": -0.2823653533025358,
      "delta_E": 0.0008499471011256254,
      "best_edge_projection_after": 0.6194440283360204,
      "best_corner_projection_after": 0.28111379923523
    },
    {
      "point_id": "v_0p70_t_0p70_lm_1p00",
      "group_id": 25,
      "dim": 2,
      "E_min": -0.2564359564098493,
      "E_max": -0.2564359564098492,
      "delta_E": 1.1102230246251565e-16,
      "best_edge_projection_after": 0.5306474131815393,
      "best_corner_projection_after": 0.15331742399030585
    },
    {
      "point_id": "v_0p70_t_0p70_lm_1p00",
      "group_id": 26,
      "dim": 4,
      "E_min": -0.25165933808932806,
      "E_max": -0.24985241283268253,
      "delta_E": 0.0018069252566455252,
      "best_edge_projection_after": 0.4232346224780526,
      "best_corner_projection_after": 0.131251505270576
    },
    {
      "point_id": "v_0p70_t_0p70_lm_1p00",
      "group_id": 27,
      "dim": 2,
      "E_min": -0.23677271386679866,
      "E_max": -0.23677271386679397,
      "delta_E": 4.690692279041286e-15,
      "best_edge_projection_after": 0.3410567196481955,
      "best_corner_projection_after": 0.08284421831651123
    },
    {
      "point_id": "v_0p70_t_0p70_lm_1p00",
      "group_id": 28,
      "dim": 4,
      "E_min": -0.2268750602666814,
      "E_max": -0.22684690601776675,
      "delta_E": 2.8154248914641355e-05,
      "best_edge_projection_after": 0.43387994112345946,
      "best_corner_projection_after": 0.1000550391843037
    },
    {
      "point_id": "v_0p70_t_0p70_lm_1p00",
      "group_id": 29,
      "dim": 2,
      "E_min": -0.22343086555429026,
      "E_max": -0.22343086555428826,
      "delta_E": 1.9984014443252818e-15,
      "best_edge_projection_after": 0.44179676795430395,
      "best_corner_projection_after": 0.0819753961320733
    },
    {
      "point_id": "v_0p70_t_0p70_lm_1p00",
      "group_id": 30,
      "dim": 4,
      "E_min": -0.2186783874199559,
      "E_max": -0.21690687754921123,
      "delta_E": 0.0017715098707446753,
      "best_edge_projection_after": 0.2605932393687838,
      "best_corner_projection_after": 0.055824253963476324
    },
    {
      "point_id": "v_0p70_t_0p70_lm_1p00",
      "group_id": 31,
      "dim": 2,
      "E_min": -0.20225628377110827,
      "E_max": -0.20225628377110721,
      "delta_E": 1.0547118733938987e-15,
      "best_edge_projection_after": 0.8096341547428492,
      "best_corner_projection_after": 0.2915122096898496
    },
    {
      "point_id": "v_0p70_t_0p70_lm_1p00",
      "group_id": 32,
      "dim": 2,
      "E_min": -0.18192653124514926,
      "E_max": -0.1819265312451487,
      "delta_E": 5.551115123125783e-16,
      "best_edge_projection_after": 0.37462637341704186,
      "best_corner_projection_after": 0.18852784703519612
    },
    {
      "point_id": "v_0p70_t_0p70_lm_1p00",
      "group_id": 33,
      "dim": 4,
      "E_min": -0.17996722877793705,
      "E_max": -0.1782365116422033,
      "delta_E": 0.0017307171357337503,
      "best_edge_projection_after": 0.4792352132901136,
      "best_corner_projection_after": 0.059464897714264935
    },
    {
      "point_id": "v_0p70_t_0p70_lm_1p00",
      "group_id": 34,
      "dim": 6,
      "E_min": -0.15249387399463835,
      "E_max": -0.15205285370795288,
      "delta_E": 0.00044102028668546733,
      "best_edge_projection_after": 0.4373378945880991,
      "best_corner_projection_after": 0.17698092854534112
    },
    {
      "point_id": "v_0p70_t_0p70_lm_1p00",
      "group_id": 35,
      "dim": 2,
      "E_min": -0.13939534964054015,
      "E_max": -0.13939534964053915,
      "delta_E": 9.992007221626409e-16,
      "best_edge_projection_after": 0.25454977963194664,
      "best_corner_projection_after": 0.043431404293478325
    },
    {
      "point_id": "v_0p70_t_0p70_lm_1p00",
      "group_id": 36,
      "dim": 2,
      "E_min": -0.136009998027593,
      "E_max": -0.1360099980275928,
      "delta_E": 1.942890293094024e-16,
      "best_edge_projection_after": 0.34602521219178056,
      "best_corner_projection_after": 0.07590000187182055
    },
    {
      "point_id": "v_0p70_t_0p70_lm_1p00",
      "group_id": 37,
      "dim": 2,
      "E_min": -0.12400083448861679,
      "E_max": -0.12400083448861647,
      "delta_E": 3.191891195797325e-16,
      "best_edge_projection_after": 0.5466802465741601,
      "best_corner_projection_after": 0.059230769075551234
    },
    {
      "point_id": "v_0p70_t_0p70_lm_1p00",
      "group_id": 38,
      "dim": 2,
      "E_min": -0.11704613359942224,
      "E_max": -0.11704613359942063,
      "delta_E": 1.609823385706477e-15,
      "best_edge_projection_after": 0.4697478464645052,
      "best_corner_projection_after": 0.10361779633439852
    },
    {
      "point_id": "v_0p70_t_0p70_lm_1p00",
      "group_id": 39,
      "dim": 2,
      "E_min": -0.10124868217256501,
      "E_max": -0.10124868217256454,
      "delta_E": 4.718447854656915e-16,
      "best_edge_projection_after": 0.48091580361482755,
      "best_corner_projection_after": 0.2528320959779979
    },
    {
      "point_id": "v_0p70_t_0p70_lm_1p00",
      "group_id": 40,
      "dim": 2,
      "E_min": -0.0807989257099058,
      "E_max": -0.08079892570990524,
      "delta_E": 5.551115123125783e-16,
      "best_edge_projection_after": 0.32566348105526766,
      "best_corner_projection_after": 0.13695360684423705
    },
    {
      "point_id": "v_0p70_t_0p70_lm_1p00",
      "group_id": 41,
      "dim": 2,
      "E_min": -0.07565350194593239,
      "E_max": -0.0756535019459312,
      "delta_E": 1.1796119636642288e-15,
      "best_edge_projection_after": 0.3930102588976767,
      "best_corner_projection_after": 0.03905381419543622
    },
    {
      "point_id": "v_0p70_t_0p70_lm_1p00",
      "group_id": 42,
      "dim": 2,
      "E_min": -0.07270395260774097,
      "E_max": -0.07270395260774065,
      "delta_E": 3.191891195797325e-16,
      "best_edge_projection_after": 0.5613087308670094,
      "best_corner_projection_after": 0.09428702492789932
    },
    {
      "point_id": "v_0p70_t_0p70_lm_1p00",
      "group_id": 43,
      "dim": 2,
      "E_min": -0.059171788343213315,
      "E_max": -0.05917178834321311,
      "delta_E": 2.0816681711721685e-16,
      "best_edge_projection_after": 0.300711964652605,
      "best_corner_projection_after": 0.06393814682197613
    },
    {
      "point_id": "v_0p70_t_0p70_lm_1p00",
      "group_id": 44,
      "dim": 2,
      "E_min": -0.056953008241905315,
      "E_max": -0.05695300824190521,
      "delta_E": 1.0408340855860843e-16,
      "best_edge_projection_after": 0.43685505701151817,
      "best_corner_projection_after": 0.03145329877716287
    },
    {
      "point_id": "v_0p70_t_0p70_lm_1p00",
      "group_id": 45,
      "dim": 2,
      "E_min": -0.04777826305450798,
      "E_max": -0.04777826305450796,
      "delta_E": 2.0816681711721685e-17,
      "best_edge_projection_after": 0.7093214974185517,
      "best_corner_projection_after": 0.3989524086965477
    },
    {
      "point_id": "v_0p70_t_0p70_lm_1p00",
      "group_id": 46,
      "dim": 2,
      "E_min": -0.0176758788628891,
      "E_max": -0.017675878862889075,
      "delta_E": 2.42861286636753e-17,
      "best_edge_projection_after": 0.7553916310478795,
      "best_corner_projection_after": 0.1383634065484925
    },
    {
      "point_id": "v_0p70_t_0p70_lm_1p00",
      "group_id": 47,
      "dim": 2,
      "E_min": -0.010900710690842282,
      "E_max": -0.010900710690842256,
      "delta_E": 2.6020852139652106e-17,
      "best_edge_projection_after": 0.32974893187260024,
      "best_corner_projection_after": 0.04503182308873862
    },
    {
      "point_id": "v_0p70_t_0p70_lm_1p00",
      "group_id": 48,
      "dim": 2,
      "E_min": -0.0009701180171764385,
      "E_max": -0.0009701180171764372,
      "delta_E": 1.3010426069826053e-18,
      "best_edge_projection_after": 0.3973764198159414,
      "best_corner_projection_after": 0.23423770636344632
    },
    {
      "point_id": "v_0p70_t_0p70_lm_1p00",
      "group_id": 49,
      "dim": 2,
      "E_min": 0.017065642022150846,
      "E_max": 0.0170656420221509,
      "delta_E": 5.551115123125783e-17,
      "best_edge_projection_after": 0.4014003111566443,
      "best_corner_projection_after": 0.06800298901845858
    },
    {
      "point_id": "v_0p70_t_0p70_lm_1p00",
      "group_id": 50,
      "dim": 2,
      "E_min": 0.02063468135865232,
      "E_max": 0.02063468135865244,
      "delta_E": 1.1796119636642288e-16,
      "best_edge_projection_after": 0.321256836820828,
      "best_corner_projection_after": 0.04174943734237758
    },
    {
      "point_id": "v_0p70_t_0p70_lm_1p00",
      "group_id": 51,
      "dim": 2,
      "E_min": 0.03578109465820633,
      "E_max": 0.035781094658206475,
      "delta_E": 1.457167719820518e-16,
      "best_edge_projection_after": 0.704499415060396,
      "best_corner_projection_after": 0.15463161850283666
    },
    {
      "point_id": "v_0p70_t_0p70_lm_1p00",
      "group_id": 52,
      "dim": 2,
      "E_min": 0.05594984786271892,
      "E_max": 0.055949847862719525,
      "delta_E": 6.036837696399289e-16,
      "best_edge_projection_after": 0.3279175113719102,
      "best_corner_projection_after": 0.1543402543007506
    },
    {
      "point_id": "v_0p70_t_0p70_lm_1p00",
      "group_id": 53,
      "dim": 2,
      "E_min": 0.08690117365357138,
      "E_max": 0.08690117365357197,
      "delta_E": 5.967448757360216e-16,
      "best_edge_projection_after": 0.5931054057019906,
      "best_corner_projection_after": 0.13627286989824178
    },
    {
      "point_id": "v_0p70_t_0p70_lm_1p00",
      "group_id": 54,
      "dim": 2,
      "E_min": 0.09254570472894064,
      "E_max": 0.09254570472894093,
      "delta_E": 2.914335439641036e-16,
      "best_edge_projection_after": 0.2342582246428787,
      "best_corner_projection_after": 0.007138420490034943
    },
    {
      "point_id": "v_0p70_t_0p70_lm_1p00",
      "group_id": 55,
      "dim": 2,
      "E_min": 0.09576991522521609,
      "E_max": 0.09576991522521675,
      "delta_E": 6.522560269672795e-16,
      "best_edge_projection_after": 0.28335158058906673,
      "best_corner_projection_after": 0.10236664155093173
    },
    {
      "point_id": "v_0p70_t_0p70_lm_1p00",
      "group_id": 56,
      "dim": 2,
      "E_min": 0.13754561741552218,
      "E_max": 0.13754561741552312,
      "delta_E": 9.43689570931383e-16,
      "best_edge_projection_after": 0.4996759201428582,
      "best_corner_projection_after": 0.11644443241959578
    },
    {
      "point_id": "v_0p70_t_0p70_lm_1p00",
      "group_id": 57,
      "dim": 2,
      "E_min": 0.1607690697538792,
      "E_max": 0.1607690697538795,
      "delta_E": 3.0531133177191805e-16,
      "best_edge_projection_after": 0.2104358885879812,
      "best_corner_projection_after": 0.04441226020465253
    },
    {
      "point_id": "v_0p70_t_0p70_lm_1p00",
      "group_id": 58,
      "dim": 2,
      "E_min": 0.18299209643954883,
      "E_max": 0.18299209643955142,
      "delta_E": 2.581268532253489e-15,
      "best_edge_projection_after": 0.42864398300468554,
      "best_corner_projection_after": 0.06744159397559141
    },
    {
      "point_id": "v_0p70_t_0p70_lm_1p00",
      "group_id": 59,
      "dim": 2,
      "E_min": 0.23551135282908972,
      "E_max": 0.23551135282909194,
      "delta_E": 2.220446049250313e-15,
      "best_edge_projection_after": 0.28504109444307313,
      "best_corner_projection_after": 0.03694385248610788
    },
    {
      "point_id": "v_0p70_t_0p70_lm_1p00",
      "group_id": 60,
      "dim": 2,
      "E_min": 0.3640902184003927,
      "E_max": 0.3640902184003933,
      "delta_E": 6.106226635438361e-16,
      "best_edge_projection_after": 0.2864472838789399,
      "best_corner_projection_after": 0.037046981107441534
    },
    {
      "point_id": "v_0p70_t_0p70_lm_1p00",
      "group_id": 61,
      "dim": 2,
      "E_min": 0.41561987261041033,
      "E_max": 0.41561987261041516,
      "delta_E": 4.829470157119431e-15,
      "best_edge_projection_after": 0.4225265474111938,
      "best_corner_projection_after": 0.06623410301196989
    },
    {
      "point_id": "v_0p70_t_0p70_lm_1p00",
      "group_id": 62,
      "dim": 2,
      "E_min": 0.4372724822653602,
      "E_max": 0.43727248226536136,
      "delta_E": 1.1657341758564144e-15,
      "best_edge_projection_after": 0.19829162970114603,
      "best_corner_projection_after": 0.0416233963259734
    },
    {
      "point_id": "v_0p70_t_0p70_lm_1p00",
      "group_id": 63,
      "dim": 2,
      "E_min": 0.45975656097199386,
      "E_max": 0.45975656097199574,
      "delta_E": 1.887379141862766e-15,
      "best_edge_projection_after": 0.4964570543649212,
      "best_corner_projection_after": 0.11506111713174402
    },
    {
      "point_id": "v_0p70_t_0p70_lm_1p00",
      "group_id": 64,
      "dim": 4,
      "E_min": 0.5000258959273064,
      "E_max": 0.5030497707085375,
      "delta_E": 0.0030238747812311173,
      "best_edge_projection_after": 0.2735800443478028,
      "best_corner_projection_after": 0.09829612544086967
    },
    {
      "point_id": "v_0p70_t_0p70_lm_1p00",
      "group_id": 65,
      "dim": 2,
      "E_min": 0.508362605407936,
      "E_max": 0.5083626054079391,
      "delta_E": 3.1086244689504383e-15,
      "best_edge_projection_after": 0.5853218163134004,
      "best_corner_projection_after": 0.13359662884050505
    }
  ]
}